comanage_nacha/__init__.py
comanage_nacha/addenda.py
comanage_nacha/batch.py
comanage_nacha/entry.py
comanage_nacha/error_codes.py
comanage_nacha/nacha_file.py
comanage_nacha/parser.py
comanage_nacha/entries/__init__.py
comanage_nacha/entries/company_batch_control.py
comanage_nacha/entries/company_batch_header.py
comanage_nacha/entries/entry_addenda.py
comanage_nacha/entries/entry_detail.py
comanage_nacha/entries/entrybase.py
comanage_nacha/entries/file_control.py
comanage_nacha/entries/file_header.py
comanage_nacha/utils/__init__.py
comanage_nacha/utils/check_digit.py
comanage_nacha/utils/confirmation_file.py
comanage_nacha-0.1.0.dist-info/DESCRIPTION.rst
comanage_nacha-0.1.0.dist-info/METADATA
comanage_nacha-0.1.0.dist-info/RECORD
comanage_nacha-0.1.0.dist-info/WHEEL
comanage_nacha-0.1.0.dist-info/metadata.json
comanage_nacha-0.1.0.dist-info/top_level.txt
